Hurley/__init__.py
Hurley/abstractClasses.py
Hurley/clustering.py
Hurley/matrix.py
Hurley/sgd.py
Hurley/testClustering.py
Hurley/testMatrix.py
Hurley/testSGD.py
Hurley/testVector.py
Hurley/vector.py
Hurley-0.0.1.dist-info/LICENSE
Hurley-0.0.1.dist-info/METADATA
Hurley-0.0.1.dist-info/WHEEL
Hurley-0.0.1.dist-info/top_level.txt
Hurley-0.0.1.dist-info/RECORD
